{
  "objectInfo" : {
    "id" : "6xPJyKI0Yimb2jmLzfBFqp",
    "name" : "Mapping6",
    "type" : "DTEMPLATE",
    "metadata" : {
      "modelVersion" : {
        "major" : 0,
        "minor" : 0
      },
      "repoInfo" : {
        "repoHandle" : "01CKSP1700000000000F"
      },
      "contextAttributes" : [ {
        "name" : "id",
        "value" : "@1"
      } ],
      "additionalInfo" : {
        "description" : "Comment Added to 6\nComment Added 6 -- 2",
        "contentType" : "JSON",
        "documentState" : "INVALID"
      }
    }
  },
  "dataFileExtension" : "zip",
  "updateTime" : "2023-08-11T14:45:08.144Z",
  "objectRefs" : [ ]
}